[
  {
    "op": "same",
    "urn": "urn:pulumi:import::github-settings::pulumi:pulumi:Stack::github-settings-import",
    "oldState": {
      "urn": "urn:pulumi:import::github-settings::pulumi:pulumi:Stack::github-settings-import",
      "custom": false,
      "type": "pulumi:pulumi:Stack"
    },
    "newState": {
      "urn": "urn:pulumi:import::github-settings::pulumi:pulumi:Stack::github-settings-import",
      "custom": false,
      "type": "pulumi:pulumi:Stack"
    },
    "detailedDiff": null
  }
]
